{
    "success": true,
    "timestamp": 1703248443,
    "base": "EUR",
    "date": "2023-12-22",
    "rates": {
        "AED": 4.050154,
        "AFN": 77.147234,
        "ALL": 103.761611,
        "AMD": 446.049913,
        "ANG": 1.987322,
        "AOA": 917.05184,
        "ARS": 886.982485,
        "AUD": 1.6188,
        "AWG": 1.985199,
        "AZN": 1.857001,
        "BAM": 1.955983,
        "BBD": 2.226409,
        "BDT": 121.021348,
        "BGN": 1.957505,
        "BHD": 0.41572,
        "BIF": 3139.994425,
        "BMD": 1.102888,
        "BND": 1.459537,
        "BOB": 7.619853,
        "BRL": 5.375809,
        "BSD": 1.102703,
        "BTC": 2.5301848e-05,
        "BTN": 91.680459,
        "BWP": 14.781386,
        "BYN": 3.632841,
        "BYR": 21616.612905,
        "BZD": 2.222708,
        "CAD": 1.463594,
        "CDF": 3154.260592,
        "CHF": 0.94115,
        "CLF": 0.03512,
        "CLP": 968.721684,
        "CNY": 7.861494,
        "COP": 4355.218114,
        "CRC": 574.464283,
        "CUC": 1.102888,
        "CUP": 29.226543,
        "CVE": 110.27534,
        "CZK": 24.580059,
        "DJF": 196.328409,
        "DKK": 7.455702,
        "DOP": 63.515956,
        "DZD": 148.218246,
        "EGP": 34.085094,
        "ERN": 16.543326,
        "ETB": 62.090848,
        "EUR": 1,
        "FJD": 2.421888,
        "FKP": 0.870577,
        "GBP": 0.866418,
        "GEL": 2.966877,
        "GGP": 0.870577,
        "GHS": 13.232481,
        "GIP": 0.870577,
        "GMD": 74.27932,
        "GNF": 9478.888798,
        "GTQ": 8.622809,
        "GYD": 230.705816,
        "HKD": 8.616812,
        "HNL": 27.201551,
        "HRK": 7.700114,
        "HTG": 145.563649,
        "HUF": 381.943483,
        "IDR": 17010.234013,
        "ILS": 3.978598,
        "IMP": 0.870577,
        "INR": 91.682672,
        "IQD": 1444.535448,
        "IRR": 46610.82161,
        "ISK": 150.489471,
        "JEP": 0.870577,
        "JMD": 170.916026,
        "JOD": 0.782388,
        "JPY": 156.579825,
        "KES": 170.959255,
        "KGS": 98.405198,
        "KHR": 4523.424144,
        "KMF": 493.318199,
        "KPW": 992.595145,
        "KRW": 1430.595129,
        "KWD": 0.338808,
        "KYD": 0.918886,
        "KZT": 505.917438,
        "LAK": 22674.537287,
        "LBP": 16573.554585,
        "LKR": 358.933656,
        "LRD": 207.729009,
        "LSL": 20.249097,
        "LTL": 3.256542,
        "LVL": 0.667126,
        "LYD": 5.290496,
        "MAD": 10.902722,
        "MDL": 19.407172,
        "MGA": 5080.568517,
        "MKD": 61.602623,
        "MMK": 2315.617126,
        "MNT": 3788.776854,
        "MOP": 8.874893,
        "MRU": 43.65265,
        "MUR": 48.516055,
        "MVR": 16.929396,
        "MWK": 1856.20771,
        "MXN": 18.720764,
        "MYR": 5.108555,
        "MZN": 69.757637,
        "NAD": 20.249368,
        "NGN": 995.698646,
        "NIO": 40.353784,
        "NOK": 11.281103,
        "NPR": 146.685754,
        "NZD": 1.749798,
        "OMR": 0.424555,
        "PAB": 1.102723,
        "PEN": 4.072282,
        "PGK": 4.114386,
        "PHP": 61.204238,
        "PKR": 307.647347,
        "PLN": 4.343215,
        "PYG": 8124.761827,
        "QAR": 4.015341,
        "RON": 4.969837,
        "RSD": 117.194989,
        "RUB": 101.36482,
        "RWF": 1385.029869,
        "SAR": 4.136856,
        "SBD": 9.308567,
        "SCR": 14.832068,
        "SDG": 662.836068,
        "SEK": 11.08425,
        "SGD": 1.459381,
        "SHP": 1.396974,
        "SLE": 25.016968,
        "SLL": 21782.045717,
        "SOS": 629.749295,
        "SRD": 40.99932,
        "STD": 22827.563437,
        "SYP": 14339.358352,
        "SZL": 20.290903,
        "THB": 38.086597,
        "TJS": 12.057831,
        "TMT": 3.860109,
        "TND": 3.39965,
        "TOP": 2.578829,
        "TRY": 32.218236,
        "TTD": 7.501839,
        "TWD": 34.308663,
        "TZS": 2773.764141,
        "UAH": 41.337876,
        "UGX": 4149.389072,
        "USD": 1.102888,
        "UYU": 43.524081,
        "UZS": 13656.280496,
        "VEF": 3935134.557905,
        "VES": 39.420203,
        "VND": 26745.044028,
        "VUV": 130.676607,
        "WST": 2.987368,
        "XAF": 656.018512,
        "XAG": 0.045032,
        "XAU": 0.000534,
        "XCD": 2.980611,
        "XDR": 0.822577,
        "XOF": 656.018512,
        "XPF": 119.331742,
        "YER": 275.503466,
        "ZAR": 20.331472,
        "ZMK": 9927.318566,
        "ZMW": 28.003134,
        "ZWL": 355.129619
    }
}